setup.py
SeasObjects/__init__.py
SeasObjects/agents/Agent.py
SeasObjects/agents/RegistrationAgent.py
SeasObjects/agents/RegistrySearchAgent.py
SeasObjects/agents/SharingAgent.py
SeasObjects/agents/TransactionAgent.py
SeasObjects/agents/__init__.py
SeasObjects/common/Auth.py
SeasObjects/common/CONTENTTYPES.py
SeasObjects/common/COUNTRY.py
SeasObjects/common/ClassMapper.py
SeasObjects/common/ConceptDetails.py
SeasObjects/common/CryptoKeyWallet.py
SeasObjects/common/DATATYPE.py
SeasObjects/common/HttpClient.py
SeasObjects/common/HttpMessage.py
SeasObjects/common/NS.py
SeasObjects/common/PROPERTY.py
SeasObjects/common/RESOURCE.py
SeasObjects/common/SERIALIZATION.py
SeasObjects/common/SeasCrypto.py
SeasObjects/common/Tools.py
SeasObjects/common/VARIANT.py
SeasObjects/common/__init__.py
SeasObjects/factory/CommandFactory.py
SeasObjects/factory/Factory.py
SeasObjects/factory/NotificationFactory.py
SeasObjects/factory/RequestFactory.py
SeasObjects/factory/ResponseFactory.py
SeasObjects/factory/__init__.py
SeasObjects/model/Ability.py
SeasObjects/model/AbstractEntity.py
SeasObjects/model/Activity.py
SeasObjects/model/Address.py
SeasObjects/model/AliveRequest.py
SeasObjects/model/AliveResponse.py
SeasObjects/model/Availability.py
SeasObjects/model/Capacity.py
SeasObjects/model/Condition.py
SeasObjects/model/Controllability.py
SeasObjects/model/Coordinates.py
SeasObjects/model/Device.py
SeasObjects/model/Direction.py
SeasObjects/model/Entity.py
SeasObjects/model/Enumeration.py
SeasObjects/model/Error.py
SeasObjects/model/Evaluation.py
SeasObjects/model/GrObj.py
SeasObjects/model/Input.py
SeasObjects/model/InterfaceAddress.py
SeasObjects/model/Map.py
SeasObjects/model/Message.py
SeasObjects/model/Notification.py
SeasObjects/model/Obj.py
SeasObjects/model/ObjectInterface.py
SeasObjects/model/Offering.py
SeasObjects/model/Organization.py
SeasObjects/model/Orientation.py
SeasObjects/model/Output.py
SeasObjects/model/Parameter.py
SeasObjects/model/Person.py
SeasObjects_for_Python.egg-info/PKG-INFO
SeasObjects_for_Python.egg-info/SOURCES.txt
SeasObjects_for_Python.egg-info/dependency_links.txt
SeasObjects_for_Python.egg-info/requires.txt
SeasObjects_for_Python.egg-info/top_level.txt