Metadata-Version: 1.1
Name: SeasObjects-for-Python
Version: 1.0.8
Summary: SEAS RDF model manipulation in Python
Home-page: https://seas.asema.com
Author: Asema Electronics Ltd
Author-email: python_dev@asema.com
License: BSD
Platform: UNKNOWN
Classifier: Development Status :: 3 - Alpha
Classifier: Intended Audience :: Developers
Classifier: Operating System :: OS Independent
Classifier: Programming Language :: Python :: 2
